presyence/.python-version
presyence/__init__.py
presyence/faster.sh
presyence/main.py
presyence/reporter/__init__.py
presyence/reporter/access_static.py
presyence/reporter/inject_json_into_js.py
presyence/reporter/server.py
presyence/reporter/www/__init__.py
presyence/reporter/www/assets/__init__.py
presyence/reporter/www/assets/index.1b03d24e.css
presyence/reporter/www/assets/index.836d003b.js
presyence/reporter/www/assets/worker.da4df076.js
presyence/reporter/www/favicon.ico
presyence/reporter/www/index.html
presyence/simpletests.py
presyence/testrunner/__init__.py
presyence/testrunner/discovery.py
presyence-0.2.0.dist-info/entry_points.txt
presyence-0.2.0.dist-info/WHEEL
presyence-0.2.0.dist-info/METADATA
presyence-0.2.0.dist-info/RECORD
