Metadata-Version: 2.1
Name: presyence
Version: 0.2.0
Summary: 
Author: Rémi Connesson
Author-email: remiconnesson@gmail.com
Requires-Python: >=3.10,<4.0
Classifier: Programming Language :: Python :: 3
Classifier: Programming Language :: Python :: 3.10
Requires-Dist: fastapi (>=0.80.0,<0.81.0)
Requires-Dist: pandas (>=1.4.3,<2.0.0)
Requires-Dist: typer (>=0.6.1,<0.7.0)
Requires-Dist: uvicorn (>=0.18.3,<0.19.0)
